hybridbackend_tf115_cu100-0.7.0.dev1666332077.dist-info/RECORD
hybridbackend_tf115_cu100-0.7.0.dev1666332077.dist-info/LICENSE
hybridbackend_tf115_cu100-0.7.0.dev1666332077.dist-info/top_level.txt
hybridbackend_tf115_cu100-0.7.0.dev1666332077.dist-info/METADATA
hybridbackend_tf115_cu100-0.7.0.dev1666332077.dist-info/WHEEL
hybridbackend_tf115_cu100-0.7.0.dev1666332077.dist-info/NOTICE
hybridbackend/__init__.py
hybridbackend/run.py
hybridbackend/libhybridbackend.so
hybridbackend/torch/__init__.py
hybridbackend/common/__init__.py
hybridbackend/common/test.py
hybridbackend/tensorflow/__init__.py
hybridbackend/tensorflow/wraps.py
hybridbackend/tensorflow/libhybridbackend_tensorflow.so
hybridbackend/tensorflow/keras/__init__.py
hybridbackend/tensorflow/keras/model.py
hybridbackend/tensorflow/keras/layers/__init__.py
hybridbackend/tensorflow/metrics/accuracy.py
hybridbackend/tensorflow/metrics/__init__.py
hybridbackend/tensorflow/metrics/mean.py
hybridbackend/tensorflow/metrics/gauc.py
hybridbackend/tensorflow/metrics/auc.py
hybridbackend/tensorflow/feature_column/backend.py
hybridbackend/tensorflow/feature_column/benchmark.py
hybridbackend/tensorflow/feature_column/math_lib.c
hybridbackend/tensorflow/feature_column/__init__.py
hybridbackend/tensorflow/feature_column/default.py
hybridbackend/tensorflow/feature_column/math_lib.cpython-36m-x86_64-linux-gnu.so
hybridbackend/tensorflow/feature_column/feature_column.py
hybridbackend/tensorflow/feature_column/dense_features.py
hybridbackend/tensorflow/feature_column/lookup.py
hybridbackend/tensorflow/pipeline/benchmark.py
hybridbackend/tensorflow/pipeline/pipeline_lib.cpython-36m-x86_64-linux-gnu.so
hybridbackend/tensorflow/pipeline/pipeline_lib.c
hybridbackend/tensorflow/pipeline/__init__.py
hybridbackend/tensorflow/framework/ops.py
hybridbackend/tensorflow/framework/__init__.py
hybridbackend/tensorflow/framework/context.py
hybridbackend/tensorflow/framework/options.py
hybridbackend/tensorflow/framework/version.py
hybridbackend/tensorflow/framework/device.py
hybridbackend/tensorflow/framework/rewriting.py
hybridbackend/tensorflow/distribute/gradient.py
hybridbackend/tensorflow/distribute/__init__.py
hybridbackend/tensorflow/distribute/pubsub.py
hybridbackend/tensorflow/distribute/communicator.py
hybridbackend/tensorflow/distribute/communicator_pool.py
